README.md
pyproject.toml
setup.cfg
src/calculator_1045059cd2b3a1bc/__init__.py
src/calculator_1045059cd2b3a1bc/calculator.py
src/calculator_1045059cd2b3a1bc.egg-info/PKG-INFO
src/calculator_1045059cd2b3a1bc.egg-info/SOURCES.txt
src/calculator_1045059cd2b3a1bc.egg-info/dependency_links.txt
src/calculator_1045059cd2b3a1bc.egg-info/top_level.txt